Metadata-Version: 1.0
Name: remixdata
Version: 0.0.1
Summary: Tools, requirements, utilities for Remix data use.
Home-page: https://github.com/remix/data-tools
Author: Michal Migurski
Author-email: mike@remix.com
License: UNKNOWN
Platform: UNKNOWN
